cdd_utils/__init__.py
cdd_utils/cli.py
cdd_utils/utf8_fix.py
cdd_utils/_utf8_backups_20251231_152741/cdd_utils/cli.py
cdd_utils/_utf8_backups_20251231_153002/cdd_utils/utf8_fix.py
cdd_utils-0.1.1.dist-info/licenses/LICENSE
cdd_utils-0.1.1.dist-info/METADATA
cdd_utils-0.1.1.dist-info/WHEEL
cdd_utils-0.1.1.dist-info/entry_points.txt
cdd_utils-0.1.1.dist-info/top_level.txt
cdd_utils-0.1.1.dist-info/RECORD
