Metadata-Version: 2.4
Name: cdd-utils
Version: 0.1.1
Summary: General utilities for AI-assisted development
Author: Gareth Millar
License: MIT
Project-URL: Homepage, https://github.com/thegdyne/cdd-utils
Project-URL: Repository, https://github.com/thegdyne/cdd-utils
Keywords: cdd,ai,development,utilities,utf8,encoding
Classifier: Development Status :: 4 - Beta
Classifier: Intended Audience :: Developers
Classifier: License :: OSI Approved :: MIT License
Classifier: Programming Language :: Python :: 3
Classifier: Programming Language :: Python :: 3.10
Classifier: Programming Language :: Python :: 3.11
Classifier: Programming Language :: Python :: 3.12
Classifier: Topic :: Software Development :: Quality Assurance
Requires-Python: >=3.10
License-File: LICENSE
Provides-Extra: dev
Requires-Dist: pytest>=7.0; extra == "dev"
Requires-Dist: pytest-cov; extra == "dev"
Dynamic: license-file
